doplcommunicator/__init__.py
doplcommunicator/controllerdata.py
doplcommunicator/depthcameradata.py
doplcommunicator/doplcommunicator.py
doplcommunicator/networkdata.py
doplcommunicator/pose.py
doplcommunicator/quaternion.py
doplcommunicator/robotdata.py
doplcommunicator/rwlock.py
doplcommunicator/vector3.py
doplcommunicator-1.0.22.dist-info/licenses/LICENSE.txt
doplcommunicator-1.0.22.dist-info/METADATA
doplcommunicator-1.0.22.dist-info/WHEEL
doplcommunicator-1.0.22.dist-info/top_level.txt
doplcommunicator-1.0.22.dist-info/RECORD
