Metadata-Version: 2.4
Name: doplcommunicator
Version: 1.0.22
Summary: Communicates data between dopl and devices
Home-page: https://github.com/dopl-technologies/data-communicator-client
Author: Ryan James, PhD
License-File: LICENSE.txt
Requires-Dist: python-socketio
Requires-Dist: requests
Requires-Dist: websocket-client
Requires-Dist: numpy
Dynamic: author
Dynamic: description
Dynamic: description-content-type
Dynamic: home-page
Dynamic: license-file
Dynamic: requires-dist
Dynamic: summary
